dwainesqol/__init__.py
dwainesqol/main.py
dwainesqol/msgbox.py
dwainesqol-0.4.dist-info/METADATA
dwainesqol-0.4.dist-info/WHEEL
dwainesqol-0.4.dist-info/top_level.txt
dwainesqol-0.4.dist-info/RECORD
