Metadata-Version: 2.1
Name: dwainesqol
Version: 0.4
